selfies/__init__.py
selfies/bond_constraints.py
selfies/compatibility.py
selfies/constants.py
selfies/decoder.py
selfies/encoder.py
selfies/exceptions.py
selfies/grammar_rules.py
selfies/mol_graph.py
selfies/utils/__init__.py
selfies/utils/encoding_utils.py
selfies/utils/matching_utils.py
selfies/utils/selfies_utils.py
selfies/utils/smiles_utils.py
selfies-2.1.2.dist-info/LICENSE
selfies-2.1.2.dist-info/METADATA
selfies-2.1.2.dist-info/WHEEL
selfies-2.1.2.dist-info/top_level.txt
selfies-2.1.2.dist-info/RECORD
