Metadata-Version: 2.1
Name: selfies
Version: 2.1.2
Summary: SELFIES (SELF-referencIng Embedded Strings) is a general-purpose, sequence-based, robust representation of semantically constrained graphs.
Home-page: https://github.com/aspuru-guzik-group/selfies
Author: Mario Krenn, Alston Lo, and many other contributors
Author-email: mario.krenn@utoronto.ca, alan@aspuru.com
Classifier: Programming Language :: Python :: 3
Classifier: Programming Language :: Python :: 3.7
Classifier: Programming Language :: Python :: 3.8
Classifier: Programming Language :: Python :: 3.9
Classifier: Programming Language :: Python :: 3.10
Classifier: Programming Language :: Python :: 3 :: Only
Classifier: License :: OSI Approved :: Apache Software License
Classifier: Operating System :: OS Independent
Requires-Python: >=3.7
License-File: LICENSE
